roboradar/RoboRadarConfig.json
roboradar/__init__.py
roboradar/__main__.py
roboradar/config.py
roboradar/dynamic_shape.py
roboradar/icon.ico
roboradar/icon.png
roboradar/fields/FRC_2020.py
roboradar/fields/__init__.py
roboradar/robots/__init__.py
roboradar/robots/standard.py
roboradar/utils/__init__.py
roboradar/utils/dummyboxbot.py
roboradar-0.3.0.dist-info/LICENSE
roboradar-0.3.0.dist-info/METADATA
roboradar-0.3.0.dist-info/WHEEL
roboradar-0.3.0.dist-info/top_level.txt
roboradar-0.3.0.dist-info/RECORD
