Metadata-Version: 2.1
Name: roboradar
Version: 0.3.0
Summary: Robot position display software for FRC
Home-page: https://github.com/Short-SirKit-6527/RoboRadar
Author: David Johnston
Author-email: dwjgame11@gmail.com
License: UNKNOWN
Platform: UNKNOWN
Classifier: Programming Language :: Python :: 3
Classifier: License :: OSI Approved :: GNU General Public License v3 (GPLv3)
Classifier: Operating System :: OS Independent
Requires-Python: >=3.6
Requires-Dist: pynetworktables
Requires-Dist: pint
